Workbook

Sheet Notice
A1: Matrice des risques projet : mode d'emploi
A3: 1 | B3: Cet outil sert à recenser, coter et suivre les risques d'un projet de construction, de l'étude jusqu'à la réception.
A4: 2 | B4: Un risque par ligne dans la feuille Registre : décris-le comme un événement possible, pas comme un constat déjà survenu.
A5: 3 | B5: Cote la probabilité et l'impact avec les échelles ci-dessous (1 à 5 chacune) : ne pas écraser la colonne criticité, elle se calcule seule.
A6: 4 | B6: Choisis la stratégie de traitement dans la liste déroulante : éviter, réduire, transférer ou accepter, puis détaille les mesures concrètes.
A7: 5 | B7: Mets à jour le statut (ouvert, en cours, clos) à chaque séance de coordination : la feuille Matrice ne compte que les risques non clos.
A8: 6 | B8: La feuille Matrice te donne en un coup d'œil où se concentrent les risques non clos du projet, par croisement probabilité x impact.
A9: 7 | B9: Revois le registre à chaque jalon du projet (études, appel d'offres, exécution, réception) : un risque clos peut en faire apparaître un autre.
A10: 8 | B10: Un risque en zone rouge exige une mesure immédiate et un responsable nommé, pas seulement une ligne de texte.
A11: 9 | B11: Ne supprime jamais une ligne close : garde l'historique, il sert à l'analyse de fin de projet et aux projets suivants.
A12: 10 | B12: Cet outil ne remplace pas une analyse de risques contractuelle exigée par un mandat (SIA, marché public) : adapte-le au cahier des charges.
A14: Échelle de probabilité (1 à 5)
A15: Niveau | B15: Définition
A16: 1 : Très improbable | B16: N'est quasiment jamais observé sur ce type de projet.
A17: 2 : Improbable | B17: Peut survenir mais reste rare dans l'expérience du secteur.
A18: 3 : Possible | B18: Se produit régulièrement sur des projets comparables.
A19: 4 : Probable | B19: Déjà rencontré sur la plupart des projets similaires.
A20: 5 : Quasi certain | B20: Se produira presque sûrement sans action préventive.
A22: Échelle d'impact (1 à 5)
A23: Niveau | B23: Définition
A24: 1 : Négligeable | B24: Aucune conséquence notable sur coût, délai ou qualité.
A25: 2 : Mineur | B25: Écart absorbable sans révision du planning ni du budget.
A26: 3 : Modéré | B26: Retard ou surcoût gérable avec les réserves du projet.
A27: 4 : Majeur | B27: Dépassement significatif de délai, de budget ou de qualité.
A28: 5 : Critique | B28: Remet en cause l'objectif, le budget ou le délai du projet.
A30: Code couleur de la criticité (probabilité x impact)
A31: Criticité de 1 à 6 | B31: Risque mineur : suivi de routine.
A32: Criticité de 7 à 12 | B32: Risque significatif : mesures de réduction actives, suivi rapproché.
A33: Criticité de 13 à 25 | B33: Risque majeur : action immédiate, information du maître d'ouvrage.

Sheet Registre
A1: ID | B1: Description du risque | C1: Catégorie | D1: Probabilité (1-5) | E1: Impact (1-5) | F1: Criticité | G1: Stratégie | H1: Mesures | I1: Responsable | J1: Échéance | K1: Statut
A2: 1 | B2: Pollution du terrain découverte lors des fouilles (hydrocarbures, métaux lourds) | C2: technique | D2: 3 | E2: 4 | F2: =D2*E2 | G2: réduire | H2: Diagnostic géotechnique complémentaire, filière d'évacuation agréée, provision budgétaire dédiée | I2: Direction des travaux | J2: 30.09.2026 | K2: ouvert
A3: 2 | B3: Faillite d'un sous-traitant clé en cours de chantier (étanchéité) | C3: financier | D3: 3 | E3: 5 | F3: =D3*E3 | G3: transférer | H3: Garantie bancaire d'exécution exigée, clause de résiliation immédiate, second sous-traitant identifié en réserve | I3: Chef de projet | J3: 31.12.2026 | K3: ouvert
A4: 3 | B4: Retard d'obtention du permis de construire (opposition ou complément d'instruction) | C4: juridique | D4: 4 | E4: 4 | F4: =D4*E4 | G4: réduire | H4: Dossier de mise à l'enquête complet et anticipé, contact préalable avec la commune, marge de planning intégrée | I4: Chef de projet | J4: 15.10.2026 | K4: en cours
A5: 4 | B5: Hausse du prix de l'acier d'armature entre la soumission et l'exécution | C5: financier | D5: 4 | E5: 3 | F5: =D5*E5 | G5: réduire | H5: Clause de renchérissement dans les contrats CFC 211-214, suivi des indices KBOB, commande anticipée des lots sensibles | I5: Chef de projet | J5: 31.01.2027 | K5: ouvert
A6: 5 | B6: Opposition de voisinage lors de la mise à l'enquête publique | C6: juridique | D6: 3 | E6: 3 | F6: =D6*E6 | G6: réduire | H6: Séance d'information préalable des riverains, adaptation du projet sur les points sensibles (gabarit, accès chantier) | I6: Chef de projet | J6: 30.09.2026 | K6: en cours
A7: 6 | B7: Défaut de coordination entre corps de métier CVSE lors du montage des faux-plafonds | C7: technique | D7: 2 | E7: 2 | F7: =D7*E7 | G7: réduire | H7: Séances de coordination technique hebdomadaires, plans de synthèse validés avant exécution | I7: Direction des travaux | J7: 28.02.2027 | K7: ouvert
A8: 7 | B8: Non-respect du délai d'exécution du gros œuvre | C8: planning | D8: 3 | E8: 4 | F8: =D8*E8 | G8: réduire | H8: Planning détaillé avec jalons intermédiaires, pénalités contractuelles, suivi hebdomadaire de l'avancement réel | I8: Direction des travaux | J8: 31.03.2027 | K8: ouvert
A9: 8 | B9: Découverte de vestiges archéologiques lors des fouilles | C9: technique | D9: 1 | E9: 5 | F9: =D9*E9 | G9: accepter | H9: Provision de délai et de budget, coordination anticipée avec le service cantonal d'archéologie | I9: Maître d'ouvrage | J9: 31.10.2026 | K9: ouvert
A10: 9 | B10: Litige sur des travaux en régie exécutés sans bon de commande signé | C10: juridique | D10: 2 | E10: 2 | F10: =D10*E10 | G10: réduire | H10: Procédure stricte de validation des régies, bons signés avant exécution, contrôle mensuel | I10: Chef de projet | J10: 15.06.2026 | K10: clos
A11: 10 | B11: Pénurie de main-d'œuvre qualifiée sur le marché romand | C11: planning | D11: 4 | E11: 3 | F11: =D11*E11 | G11: transférer | H11: Contrats-cadres avec plusieurs entreprises, planning phasé pour lisser la charge, recours ponctuel à l'intérim spécialisé | I11: Direction des travaux | J11: 31.03.2027 | K11: en cours
A12: 11 | B12: Dépassement de budget sur les travaux spéciaux (fondations spéciales) | C12: financier | D12: 3 | E12: 4 | F12: =D12*E12 | G12: réduire | H12: Étude géotechnique préalable renforcée, provision pour risques CFC 2, validation des devis complémentaires par le MO | I12: Chef de projet | J12: 30.11.2026 | K12: ouvert
A13: 12 | B13: Sinistre lors du transport ou du grutage d'éléments préfabriqués | C13: technique | D13: 2 | E13: 3 | F13: =D13*E13 | G13: réduire | H13: Plan de levage validé par un ingénieur, assurance transport dédiée, zone de grutage balisée et sécurisée | I13: Direction des travaux | J13: 31.08.2026 | K13: clos
F14: =IF(OR(D14="",E14=""),"",D14*E14)
F15: =IF(OR(D15="",E15=""),"",D15*E15)
F16: =IF(OR(D16="",E16=""),"",D16*E16)
F17: =IF(OR(D17="",E17=""),"",D17*E17)
F18: =IF(OR(D18="",E18=""),"",D18*E18)
F19: =IF(OR(D19="",E19=""),"",D19*E19)
F20: =IF(OR(D20="",E20=""),"",D20*E20)
F21: =IF(OR(D21="",E21=""),"",D21*E21)
F22: =IF(OR(D22="",E22=""),"",D22*E22)
F23: =IF(OR(D23="",E23=""),"",D23*E23)
F24: =IF(OR(D24="",E24=""),"",D24*E24)
F25: =IF(OR(D25="",E25=""),"",D25*E25)
... F33: =IF(OR(D33="",E33=""),"",D33*E33)

Sheet Matrice
A1: Nombre de risques NON CLOS par croisement probabilité (lignes) x impact (colonnes)
B2: Probabilité \ Impact | C2: Impact 1 | D2: Impact 2 | E2: Impact 3 | F2: Impact 4 | G2: Impact 5
B3: Probabilité 1 | C3: =COUNTIFS(Registre!$D$2:$D$33,1,Registre!$E$2:$E$33,1,Registre!$K$2:$K$33,"<>clos") | D3: =COUNTIFS(Registre!$D$2:$D$33,1,Registre!$E$2:$E$33,2,Registre!$K$2:$K$33,"<>clos") | E3: =COUNTIFS(Registre!$D$2:$D$33,1,Registre!$E$2:$E$33,3,Registre!$K$2:$K$33,"<>clos") | F3: =COUNTIFS(Registre!$D$2:$D$33,1,Registre!$E$2:$E$33,4,Registre!$K$2:$K$33,"<>clos") | G3: =COUNTIFS(Registre!$D$2:$D$33,1,Registre!$E$2:$E$33,5,Registre!$K$2:$K$33,"<>clos")
B4: Probabilité 2 | C4: =COUNTIFS(Registre!$D$2:$D$33,2,Registre!$E$2:$E$33,1,Registre!$K$2:$K$33,"<>clos") | D4: =COUNTIFS(Registre!$D$2:$D$33,2,Registre!$E$2:$E$33,2,Registre!$K$2:$K$33,"<>clos") | E4: =COUNTIFS(Registre!$D$2:$D$33,2,Registre!$E$2:$E$33,3,Registre!$K$2:$K$33,"<>clos") | F4: =COUNTIFS(Registre!$D$2:$D$33,2,Registre!$E$2:$E$33,4,Registre!$K$2:$K$33,"<>clos") | G4: =COUNTIFS(Registre!$D$2:$D$33,2,Registre!$E$2:$E$33,5,Registre!$K$2:$K$33,"<>clos")
B5: Probabilité 3 | C5: =COUNTIFS(Registre!$D$2:$D$33,3,Registre!$E$2:$E$33,1,Registre!$K$2:$K$33,"<>clos") | D5: =COUNTIFS(Registre!$D$2:$D$33,3,Registre!$E$2:$E$33,2,Registre!$K$2:$K$33,"<>clos") | E5: =COUNTIFS(Registre!$D$2:$D$33,3,Registre!$E$2:$E$33,3,Registre!$K$2:$K$33,"<>clos") | F5: =COUNTIFS(Registre!$D$2:$D$33,3,Registre!$E$2:$E$33,4,Registre!$K$2:$K$33,"<>clos") | G5: =COUNTIFS(Registre!$D$2:$D$33,3,Registre!$E$2:$E$33,5,Registre!$K$2:$K$33,"<>clos")
B6: Probabilité 4 | C6: =COUNTIFS(Registre!$D$2:$D$33,4,Registre!$E$2:$E$33,1,Registre!$K$2:$K$33,"<>clos") | D6: =COUNTIFS(Registre!$D$2:$D$33,4,Registre!$E$2:$E$33,2,Registre!$K$2:$K$33,"<>clos") | E6: =COUNTIFS(Registre!$D$2:$D$33,4,Registre!$E$2:$E$33,3,Registre!$K$2:$K$33,"<>clos") | F6: =COUNTIFS(Registre!$D$2:$D$33,4,Registre!$E$2:$E$33,4,Registre!$K$2:$K$33,"<>clos") | G6: =COUNTIFS(Registre!$D$2:$D$33,4,Registre!$E$2:$E$33,5,Registre!$K$2:$K$33,"<>clos")
B7: Probabilité 5 | C7: =COUNTIFS(Registre!$D$2:$D$33,5,Registre!$E$2:$E$33,1,Registre!$K$2:$K$33,"<>clos") | D7: =COUNTIFS(Registre!$D$2:$D$33,5,Registre!$E$2:$E$33,2,Registre!$K$2:$K$33,"<>clos") | E7: =COUNTIFS(Registre!$D$2:$D$33,5,Registre!$E$2:$E$33,3,Registre!$K$2:$K$33,"<>clos") | F7: =COUNTIFS(Registre!$D$2:$D$33,5,Registre!$E$2:$E$33,4,Registre!$K$2:$K$33,"<>clos") | G7: =COUNTIFS(Registre!$D$2:$D$33,5,Registre!$E$2:$E$33,5,Registre!$K$2:$K$33,"<>clos")
