Workbook

Sheet Notice
A1: NOTICE, OUTIL SMIT DE GESTION FINANCIÈRE DE CHANTIER
B3: Cet outil sert au chef de projet à piloter mensuellement les finances d'un chantier de construction : budget, engagements, facturation, plus-values et moins-values, prévision fin de chantier (PFC), cash-flow et marge. Il est conçu pour être mis à jour chaque mois, en parallèle de la situation adressée au maître d'ouvrage (MO).
B5: À quoi sert chaque feuille
B6: Paramètres = données de base du chantier et listes utilisées dans tout le classeur. Budget = budget adjugé par position CFC, ventilé en Salaires / Matériaux / Inventaire / Tiers (SMIT). Engagements = journal des contrats et commandes passés aux entreprises. Facturation = situations mensuelles émises au MO. Régie-PV-MV = suppléments, plus-values, moins-values et réclamations. Prévision = prévision fin de chantier (PFC) et marge prévue par position. Cash-flow = suivi de la facturation et des encaissements dans le temps. Dashboard = indicateurs de synthèse avec feux tricolores. Analyse = contrôles automatiques qui signalent les points à vérifier.
B8: Routine mensuelle en 5 étapes
B9: 1. Mettre à jour la feuille Engagements : ajouter les nouveaux contrats, commandes et avenants du mois (montant engagé par position CFC et famille SMIT).
B10: 2. Mettre à jour la feuille Facturation : saisir la nouvelle situation émise au MO (montant HT du mois) et pointer les paiements reçus.
B11: 3. Mettre à jour la feuille Régie-PV-MV : ajouter les nouvelles demandes, en faire évoluer le statut (annoncé, accepté ou refusé).
B12: 4. Réviser la feuille Prévision : ajuster le reste à engager et les risques/aléas de chaque position selon l'avancement réel constaté sur le chantier.
B13: 5. Contrôler le Dashboard et la feuille Analyse : vérifier les feux tricolores et traiter chaque ALERTE avant de clôturer la situation du mois.
B15: Code couleur
B16: Fond jaune pâle : cellule de SAISIE. C'est une donnée d'entrée (date, montant, libellé, statut) que le chef de projet renseigne ou corrige chaque mois.
B17: Fond gris très clair (ou blanc) : cellule CALCULÉE. Le résultat provient d'une formule Excel et ne doit jamais être saisi ou écrasé à la main.
... B33: Sur les situations intermédiaires, la TVA est calculée sur le montant net après retenue de garantie (pratique appliquée dans cet outil). Au décompte final, elle se calcule sur le montant total, retenue restituée comprise (pratique TVA courante dans le bâtiment, cf. Actu-TVA n° 76 ; à confirmer dans tous les cas avec la fiduciaire du mandat, les pratiques pouvant varier selon les contrats).

Sheet Parametres
A1: PARAMÈTRES DU CHANTIER | E1: POSITIONS CFC (LISTE DE VALIDATION)
E2: CFC | F2: Libellé
A3: Nom du chantier | B3: Résidence Les Tilleuls | E3: 201 | F3: Fouilles et terrassements
A4: Maître d'ouvrage (MO) | B4: Coopérative immobilière Le Tilleul, Lausanne | E4: 211 | F4: Maçonnerie et béton armé
A5: Adresse | B5: Chemin des Tilleuls 12-18, 1004 Lausanne | E5: 212 | F5: Dalles et planchers béton
A6: Chef de projet | B6: Julien Rey | E6: 213 | F6: Construction métallique
A7: Date d'arrêté de la situation | B7: 46265 | E7: 214 | F7: Échafaudages
A8: Prix de vente total HT (CHF) | B8: 8000000 | E8: 221 | F8: Fenêtres et portes extérieures
A9: Marge initiale visée (%) | B9: 0.054 | E9: 222 | F9: Fermetures, volets et stores
A10: Durée totale du chantier (mois) | B10: 18 | E10: 224 | F10: Étanchéité toiture
A11: TAUX ET RÈGLES FINANCIÈRES | E11: 226 | F11: Ferblanterie
A12: Taux de TVA | B12: 0.081 | E12: 228 | F12: Isolation périphérique façade
A13: Taux de retenue de garantie | B13: 0.1 | E13: 230 | F13: Installations électriques
A14: Plafond de retenue (% du prix de vente) | B14: 0.02 | C14: usuel à la réception, selon contrat | E14: 240 | F14: Chauffage, ventilation, CVC
E15: 250 | F15: Installations sanitaires
E16: 260 | F16: Ascenseur
A17: CALENDRIER DU CHANTIER (18 MOIS) | E17: 271 | F17: Plâtrerie
A18: N° | B18: Mois | C18: Libellé | E18: 272 | F18: Serrurerie
A19: 1 | B19: 46023 | C19: Janvier 2026 | E19: 273 | F19: Menuiserie intérieure
A20: 2 | B20: 46054 | C20: Février 2026 | E20: 281 | F20: Chapes
A21: 3 | B21: 46082 | C21: Mars 2026 | E21: 282 | F21: Revêtements de sol
A22: 4 | B22: 46113 | C22: Avril 2026 | E22: 284 | F22: Carrelages
A23: 5 | B23: 46143 | C23: Mai 2026 | E23: 285 | F23: Peinture
A24: 6 | B24: 46174 | C24: Juin 2026 | E24: 287 | F24: Nettoyage de fin de chantier
A25: 7 | B25: 46204 | C25: Juillet 2026 | E25: 299 | F25: Divers, travaux imprévus (hors bordereau)
A26: 8 | B26: 46235 | C26: Août 2026
A27: 9 | B27: 46266 | C27: Septembre 2026
A28: 10 | B28: 46296 | C28: Octobre 2026
A29: 11 | B29: 46327 | C29: Novembre 2026
A30: 12 | B30: 46357 | C30: Décembre 2026
A31: 13 | B31: 46388 | C31: Janvier 2027
A32: 14 | B32: 46419 | C32: Février 2027
A33: 15 | B33: 46447 | C33: Mars 2027
A34: 16 | B34: 46478 | C34: Avril 2027
A35: 17 | B35: 46508 | C35: Mai 2027
A36: 18 | B36: 46539 | C36: Juin 2027

Sheet Budget
A1: BUDGET PAR POSITION CFC (VENTILATION SMIT)
A3: CFC | B3: Libellé | C3: Prix de vente adjugé | D3: Budget initial S | E3: Budget initial M | F3: Budget initial I | G3: Budget initial T | H3: Total ventilation SMIT | I3: Avenants budget | J3: Budget corrigé | K3: Marge initiale | L3: % Marge
A4: 201 | B4: Fouilles et terrassements | C4: 652900 | D4: 214800 | E4: 184100 | F4: 122700 | G4: 92100 | H4: =SUM(D4:G4) | I4: 0 | J4: =H4+I4 | K4: =C4-J4 | L4: =IF(C4=0,0,K4/C4)
A5: 211 | B5: Maçonnerie et béton armé | C5: 1218700 | D5: 401000 | E5: 343700 | F5: 229100 | G5: 171800 | H5: =SUM(D5:G5) | I5: 30000 | J5: =H5+I5 | K5: =C5-J5 | L5: =IF(C5=0,0,K5/C5)
A6: 212 | B6: Dalles et planchers béton | C6: 522300 | D6: 171800 | E6: 147300 | F6: 98200 | G6: 73700 | H6: =SUM(D6:G6) | I6: 0 | J6: =H6+I6 | K6: =C6-J6 | L6: =IF(C6=0,0,K6/C6)
A7: 213 | B7: Construction métallique | C7: 304700 | D7: 100200 | E7: 85900 | F7: 57300 | G7: 43000 | H7: =SUM(D7:G7) | I7: 15000 | J7: =H7+I7 | K7: =C7-J7 | L7: =IF(C7=0,0,K7/C7)
A8: 214 | B8: Échafaudages | C8: 104500 | D8: 34400 | E8: 29500 | F8: 19600 | G8: 14700 | H8: =SUM(D8:G8) | I8: 0 | J8: =H8+I8 | K8: =C8-J8 | L8: =IF(C8=0,0,K8/C8)
A9: 221 | B9: Fenêtres et portes extérieures | C9: 478800 | D9: 67500 | E9: 202500 | F9: 22500 | G9: 157600 | H9: =SUM(D9:G9) | I9: 10000 | J9: =H9+I9 | K9: =C9-J9 | L9: =IF(C9=0,0,K9/C9)
A10: 222 | B10: Fermetures, volets et stores | C10: 130600 | D10: 18400 | E10: 55200 | F10: 6100 | G10: 43000 | H10: =SUM(D10:G10) | I10: 0 | J10: =H10+I10 | K10: =C10-J10 | L10: =IF(C10=0,0,K10/C10)
A11: 224 | B11: Étanchéité toiture | C11: 217600 | D11: 30700 | E11: 92100 | F11: 10200 | G11: 71600 | H11: =SUM(D11:G11) | I11: 0 | J11: =H11+I11 | K11: =C11-J11 | L11: =IF(C11=0,0,K11/C11)
A12: 226 | B12: Ferblanterie | C12: 104500 | D12: 14700 | E12: 44200 | F12: 4900 | G12: 34400 | H12: =SUM(D12:G12) | I12: 0 | J12: =H12+I12 | K12: =C12-J12 | L12: =IF(C12=0,0,K12/C12)
A13: 228 | B13: Isolation périphérique façade | C13: 391700 | D13: 55200 | E13: 165700 | F13: 18400 | G13: 128900 | H13: =SUM(D13:G13) | I13: 0 | J13: =H13+I13 | K13: =C13-J13 | L13: =IF(C13=0,0,K13/C13)
A14: 230 | B14: Installations électriques | C14: 652900 | D14: 30700 | E14: 61400 | F14: 12300 | G14: 509300 | H14: =SUM(D14:G14) | I14: 0 | J14: =H14+I14 | K14: =C14-J14 | L14: =IF(C14=0,0,K14/C14)
A15: 240 | B15: Chauffage, ventilation, CVC | C15: 609400 | D15: 28600 | E15: 57300 | F15: 11500 | G15: 475400 | H15: =SUM(D15:G15) | I15: 0 | J15: =H15+I15 | K15: =C15-J15 | L15: =IF(C15=0,0,K15/C15)
... A25: 287 | B25: Nettoyage de fin de chantier | C25: 86900 | D25: 20400 | E25: 28600 | F25: 8200 | G25: 24400 | H25: =SUM(D25:G25) | I25: 0 | J25: =H25+I25 | K25: =C25-J25 | L25: =IF(C25=0,0,K25/C25)
A26: TOTAL | B26: Toutes positions CFC | C26: =SUM(C4:C25) | D26: =SUM(D4:D25) | E26: =SUM(E4:E25) | F26: =SUM(F4:F25) | G26: =SUM(G4:G25) | H26: =SUM(H4:H25) | I26: =SUM(I4:I25) | J26: =SUM(J4:J25) | K26: =SUM(K4:K25) | L26: =IF(C26=0,0,K26/C26)
A28: Contrôle : colonne Total ventilation (H) intacte, non écrasée par une valeur collée ? | G28: =IF(ROUND(SUMPRODUCT(ABS(H4:H25-(D4:D25+E4:E25+F4:F25+G4:G25))),2)=0,"OK","ERREUR")

Sheet Engagements
A1: ENGAGEMENTS (CONTRATS, COMMANDES, AVENANTS)
A3: Récapitulatif par position CFC
A4: CFC | B4: Libellé | C4: Budget corrigé | D4: Engagé total | E4: Écart | F4: % Engagé
A5: ='Budget'!A4 | B5: ='Budget'!B4 | C5: =Budget!$J4 | D5: =SUMIFS($F$32:$F$82,$D$32:$D$82,A5) | E5: =C5-D5 | F5: =IF(C5=0,0,D5/C5)
A6: ='Budget'!A5 | B6: ='Budget'!B5 | C6: =Budget!$J5 | D6: =SUMIFS($F$32:$F$82,$D$32:$D$82,A6) | E6: =C6-D6 | F6: =IF(C6=0,0,D6/C6)
A7: ='Budget'!A6 | B7: ='Budget'!B6 | C7: =Budget!$J6 | D7: =SUMIFS($F$32:$F$82,$D$32:$D$82,A7) | E7: =C7-D7 | F7: =IF(C7=0,0,D7/C7)
A8: ='Budget'!A7 | B8: ='Budget'!B7 | C8: =Budget!$J7 | D8: =SUMIFS($F$32:$F$82,$D$32:$D$82,A8) | E8: =C8-D8 | F8: =IF(C8=0,0,D8/C8)
A9: ='Budget'!A8 | B9: ='Budget'!B8 | C9: =Budget!$J8 | D9: =SUMIFS($F$32:$F$82,$D$32:$D$82,A9) | E9: =C9-D9 | F9: =IF(C9=0,0,D9/C9)
A10: ='Budget'!A9 | B10: ='Budget'!B9 | C10: =Budget!$J9 | D10: =SUMIFS($F$32:$F$82,$D$32:$D$82,A10) | E10: =C10-D10 | F10: =IF(C10=0,0,D10/C10)
A11: ='Budget'!A10 | B11: ='Budget'!B10 | C11: =Budget!$J10 | D11: =SUMIFS($F$32:$F$82,$D$32:$D$82,A11) | E11: =C11-D11 | F11: =IF(C11=0,0,D11/C11)
A12: ='Budget'!A11 | B12: ='Budget'!B11 | C12: =Budget!$J11 | D12: =SUMIFS($F$32:$F$82,$D$32:$D$82,A12) | E12: =C12-D12 | F12: =IF(C12=0,0,D12/C12)
A13: ='Budget'!A12 | B13: ='Budget'!B12 | C13: =Budget!$J12 | D13: =SUMIFS($F$32:$F$82,$D$32:$D$82,A13) | E13: =C13-D13 | F13: =IF(C13=0,0,D13/C13)
A14: ='Budget'!A13 | B14: ='Budget'!B13 | C14: =Budget!$J13 | D14: =SUMIFS($F$32:$F$82,$D$32:$D$82,A14) | E14: =C14-D14 | F14: =IF(C14=0,0,D14/C14)
A15: ='Budget'!A14 | B15: ='Budget'!B14 | C15: =Budget!$J14 | D15: =SUMIFS($F$32:$F$82,$D$32:$D$82,A15) | E15: =C15-D15 | F15: =IF(C15=0,0,D15/C15)
A16: ='Budget'!A15 | B16: ='Budget'!B15 | C16: =Budget!$J15 | D16: =SUMIFS($F$32:$F$82,$D$32:$D$82,A16) | E16: =C16-D16 | F16: =IF(C16=0,0,D16/C16)
... A26: ='Budget'!A25 | B26: ='Budget'!B25 | C26: =Budget!$J25 | D26: =SUMIFS($F$32:$F$82,$D$32:$D$82,A26) | E26: =C26-D26 | F26: =IF(C26=0,0,D26/C26)
A27: 299 | B27: Divers, travaux imprévus (hors bordereau) | C27: 0 | D27: =SUMIFS($F$32:$F$82,$D$32:$D$82,A27) | E27: =C27-D27 | F27: =IF(C27=0,0,D27/C27)
A28: TOTAL | B28: Toutes positions CFC, hors bordereau inclus | C28: =SUM(C5:C27) | D28: =SUM(D5:D27) | E28: =SUM(E5:E27) | F28: =IF(C28=0,0,D28/C28)
A30: Journal des engagements
A31: Date | B31: Fournisseur / sous-traitant | C31: Description | D31: CFC | E31: Famille SMIT | F31: Montant engagé | G31: Type
A32: 46037 | B32: Terrassement Dupont SA | C32: Fouilles générales et évacuation | D32: 201 | E32: T | F32: 420000 | G32: contrat initial
A33: 46054 | B33: Béton Frais Vaudois SA | C33: Fourniture béton et armatures | D33: 211 | E33: M | F33: 850000 | G33: contrat initial
A34: 46082 | B34: Coffrages Romands Sarl | C34: Location coffrages voiles et dalles | D34: 211 | E34: I | F34: 180000 | G34: commande
A35: 46127 | B35: Béton Frais Vaudois SA | C35: Renfort armature suite étude de sol | D35: 211 | E35: M | F35: 200000 | G35: avenant
A36: 46143 | B36: Métal Constructions SA | C36: Charpente métallique et acier | D36: 213 | E36: T | F36: 260000 | G36: contrat initial
A37: 46183 | B37: Métal Constructions SA | C37: Passerelle accès complémentaire | D37: 213 | E37: T | F37: 55000 | G37: avenant
A38: 46162 | B38: Menuiserie Alu Lémanique Sarl | C38: Fenêtres et portes-fenêtres alu | D38: 221 | E38: T | F38: 410000 | G38: contrat initial
A39: 46174 | B39: Étanch'Toit SA | C39: Étanchéité toiture plate | D39: 224 | E39: T | F39: 195000 | G39: contrat initial
A40: 46188 | B40: Isolfaçade Sarl | C40: Isolation périph. et crépi façade | D40: 228 | E40: T | F40: 340000 | G40: contrat initial
A41: 46054 | B41: Élec Plus SA | C41: Installations électriques courant fort/faible | D41: 230 | E41: T | F41: 560000 | G41: contrat initial
A42: 46204 | B42: Élec Plus SA | C42: Complément tableaux électriques | D42: 230 | E42: M | F42: 25000 | G42: commande
A43: 46082 | B43: Thermoclim Sarl | C43: Production chaleur et ventilation CVC | D43: 240 | E43: T | F43: 540000 | G43: contrat initial
... A52: 46228 | B52: Divers Sarl | C52: Travaux imprévus divers hors bordereau | D52: 299 | E52: S | F52: 8500 | G52: commande

Sheet Facturation
A1: FACTURATION, SITUATIONS MENSUELLES AU MAÎTRE D'OUVRAGE
A3: Mois | B3: N° situation | C3: Montant HT situation | D3: Retenue de garantie 10% | E3: Net HT | F3: TVA 8.1% | G3: TTC | H3: Payé | I3: Date de paiement | J3: Facturé cumulé
A4: 46023 | B4: 1 | C4: 60000 | D4: =MAX(0,MIN(C4*Parametres!$B$13,(Parametres!$B$8*Parametres!$B$14))) | E4: =C4-D4 | F4: =E4*Parametres!$B$12 | G4: =E4+F4 | H4: Oui | I4: 46083 | J4: =SUM($C$4:C4)
A5: 46054 | B5: 2 | C5: 140000 | D5: =MAX(0,MIN(C5*Parametres!$B$13,(Parametres!$B$8*Parametres!$B$14-SUM($D$4:D4)))) | E5: =C5-D5 | F5: =E5*Parametres!$B$12 | G5: =E5+F5 | H5: Oui | I5: 46111 | J5: =SUM($C$4:C5)
A6: 46082 | B6: 3 | C6: 310000 | D6: =MAX(0,MIN(C6*Parametres!$B$13,(Parametres!$B$8*Parametres!$B$14-SUM($D$4:D5)))) | E6: =C6-D6 | F6: =E6*Parametres!$B$12 | G6: =E6+F6 | H6: Oui | I6: 46142 | J6: =SUM($C$4:C6)
A7: 46113 | B7: 4 | C7: 480000 | D7: =MAX(0,MIN(C7*Parametres!$B$13,(Parametres!$B$8*Parametres!$B$14-SUM($D$4:D6)))) | E7: =C7-D7 | F7: =E7*Parametres!$B$12 | G7: =E7+F7 | H7: Oui | I7: 46171 | J7: =SUM($C$4:C7)
A8: 46143 | B8: 5 | C8: 620000 | D8: =MAX(0,MIN(C8*Parametres!$B$13,(Parametres!$B$8*Parametres!$B$14-SUM($D$4:D7)))) | E8: =C8-D8 | F8: =E8*Parametres!$B$12 | G8: =E8+F8 | H8: Oui | I8: 46203 | J8: =SUM($C$4:C8)
A9: 46174 | B9: 6 | C9: 680000 | D9: =MAX(0,MIN(C9*Parametres!$B$13,(Parametres!$B$8*Parametres!$B$14-SUM($D$4:D8)))) | E9: =C9-D9 | F9: =E9*Parametres!$B$12 | G9: =E9+F9 | H9: Oui | I9: 46233 | J9: =SUM($C$4:C9)
A10: 46204 | B10: 7 | C10: 640000 | D10: =MAX(0,MIN(C10*Parametres!$B$13,(Parametres!$B$8*Parametres!$B$14-SUM($D$4:D9)))) | E10: =C10-D10 | F10: =E10*Parametres!$B$12 | G10: =E10+F10 | H10: Non | J10: =SUM($C$4:C10)
A11: 46235 | B11: 8 | C11: 590000 | D11: =MAX(0,MIN(C11*Parametres!$B$13,(Parametres!$B$8*Parametres!$B$14-SUM($D$4:D10)))) | E11: =C11-D11 | F11: =E11*Parametres!$B$12 | G11: =E11+F11 | H11: Non | J11: =SUM($C$4:C11)
A12: 46266 | D12: =MAX(0,MIN(C12*Parametres!$B$13,(Parametres!$B$8*Parametres!$B$14-SUM($D$4:D11)))) | E12: =C12-D12 | F12: =E12*Parametres!$B$12 | G12: =E12+F12 | J12: =SUM($C$4:C12)
A13: 46296 | D13: =MAX(0,MIN(C13*Parametres!$B$13,(Parametres!$B$8*Parametres!$B$14-SUM($D$4:D12)))) | E13: =C13-D13 | F13: =E13*Parametres!$B$12 | G13: =E13+F13 | J13: =SUM($C$4:C13)
A14: 46327 | D14: =MAX(0,MIN(C14*Parametres!$B$13,(Parametres!$B$8*Parametres!$B$14-SUM($D$4:D13)))) | E14: =C14-D14 | F14: =E14*Parametres!$B$12 | G14: =E14+F14 | J14: =SUM($C$4:C14)
A15: 46357 | D15: =MAX(0,MIN(C15*Parametres!$B$13,(Parametres!$B$8*Parametres!$B$14-SUM($D$4:D14)))) | E15: =C15-D15 | F15: =E15*Parametres!$B$12 | G15: =E15+F15 | J15: =SUM($C$4:C15)
A16: 46388 | D16: =MAX(0,MIN(C16*Parametres!$B$13,(Parametres!$B$8*Parametres!$B$14-SUM($D$4:D15)))) | E16: =C16-D16 | F16: =E16*Parametres!$B$12 | G16: =E16+F16 | J16: =SUM($C$4:C16)
A17: 46419 | D17: =MAX(0,MIN(C17*Parametres!$B$13,(Parametres!$B$8*Parametres!$B$14-SUM($D$4:D16)))) | E17: =C17-D17 | F17: =E17*Parametres!$B$12 | G17: =E17+F17 | J17: =SUM($C$4:C17)
A18: 46447 | D18: =MAX(0,MIN(C18*Parametres!$B$13,(Parametres!$B$8*Parametres!$B$14-SUM($D$4:D17)))) | E18: =C18-D18 | F18: =E18*Parametres!$B$12 | G18: =E18+F18 | J18: =SUM($C$4:C18)
A19: 46478 | D19: =MAX(0,MIN(C19*Parametres!$B$13,(Parametres!$B$8*Parametres!$B$14-SUM($D$4:D18)))) | E19: =C19-D19 | F19: =E19*Parametres!$B$12 | G19: =E19+F19 | J19: =SUM($C$4:C19)
A20: 46508 | D20: =MAX(0,MIN(C20*Parametres!$B$13,(Parametres!$B$8*Parametres!$B$14-SUM($D$4:D19)))) | E20: =C20-D20 | F20: =E20*Parametres!$B$12 | G20: =E20+F20 | J20: =SUM($C$4:C20)
A21: 46539 | D21: =MAX(0,MIN(C21*Parametres!$B$13,(Parametres!$B$8*Parametres!$B$14-SUM($D$4:D20)))) | E21: =C21-D21 | F21: =E21*Parametres!$B$12 | G21: =E21+F21 | J21: =SUM($C$4:C21)
A22: TOTAL | C22: =SUM(C4:C21) | D22: =SUM(D4:D21) | E22: =SUM(E4:E21) | F22: =SUM(F4:F21) | G22: =SUM(G4:G21) | J22: =J21

Sheet Regie-PV-MV
A1: RÉGIE, PLUS-VALUES, MOINS-VALUES ET RÉCLAMATIONS
A3: Récapitulatif par statut
A4: Total accepté (CHF) | B4: =SUMIFS('Regie-PV-MV'!$F$7:$F$47,'Regie-PV-MV'!$H$7:$H$47,"accepté") | D4: Total en attente, annoncé (CHF) | E4: =SUMIFS('Regie-PV-MV'!$F$7:$F$47,'Regie-PV-MV'!$H$7:$H$47,"annoncé") | G4: Total refusé (CHF) | H4: =SUMIFS('Regie-PV-MV'!$F$7:$F$47,'Regie-PV-MV'!$H$7:$H$47,"refusé")
A6: Date | B6: Référence | C6: Description | D6: Type | E6: CFC | F6: Montant vente | G6: Coût estimé | H6: Statut | I6: Inclus dans PFC
A7: 46063 | B7: REG-001 | C7: Renfort armature fondations suite étude de sol | D7: régie | E7: 211 | F7: 35000 | G7: 28000 | H7: accepté | I7: =IF(H7="accepté","oui","non")
A8: 46086 | B8: REG-002 | C8: Modification tracé gaines techniques CVC | D8: plus-value | E8: 240 | F8: 18000 | G8: 14000 | H8: accepté | I8: =IF(H8="accepté","oui","non")
A9: 46101 | B9: REG-003 | C9: Suppression cloison technique buanderie | D9: moins-value | E9: 271 | F9: -6000 | G9: -4500 | H9: accepté | I9: =IF(H9="accepté","oui","non")
A10: 46114 | B10: REG-004 | C10: Balcons supplémentaires attique | D10: offre complémentaire | E10: 213 | F10: 42000 | G10: 33000 | H10: accepté | I10: =IF(H10="accepté","oui","non")
A11: 46130 | B11: REG-005 | C11: Réclamation retard livraison fenêtres | D11: réclamation | E11: 221 | F11: 0 | G11: 5000 | H11: refusé | I11: =IF(H11="accepté","oui","non")
A12: 46152 | B12: REG-006 | C12: Store extérieur supplémentaire terrasse | D12: plus-value | E12: 222 | F12: 9500 | G12: 7000 | H12: accepté | I12: =IF(H12="accepté","oui","non")
A13: 46167 | B13: REG-007 | C13: Revêtement de sol upgrade parquet chêne | D13: offre complémentaire | E13: 282 | F13: 22000 | G13: 17500 | H13: annoncé | I13: =IF(H13="accepté","oui","non")
A14: 46181 | B14: REG-008 | C14: Agencement menuiserie complémentaire cuisines | D14: offre complémentaire | E14: 273 | F14: 28000 | G14: 21000 | H14: annoncé | I14: =IF(H14="accepté","oui","non")
A15: 46195 | B15: REG-009 | C15: Régie déblaiement terre polluée imprévue | D15: régie | E15: 201 | F15: 12000 | G15: 12000 | H15: accepté | I15: =IF(H15="accepté","oui","non")
A16: 46217 | B16: REG-010 | C16: Réclamation fissures enduit façade | D16: réclamation | E16: 228 | F16: 0 | G16: 8000 | H16: annoncé | I16: =IF(H16="accepté","oui","non")
A17: 46233 | B17: REG-011 | C17: Ascenseur option cabine design | D17: plus-value | E17: 260 | F17: 15000 | G17: 11000 | H17: refusé | I17: =IF(H17="accepté","oui","non")
I18: =IF(H18="","",IF(H18="accepté","oui","non"))
I19: =IF(H19="","",IF(H19="accepté","oui","non"))
I20: =IF(H20="","",IF(H20="accepté","oui","non"))
I21: =IF(H21="","",IF(H21="accepté","oui","non"))
I22: =IF(H22="","",IF(H22="accepté","oui","non"))
I23: =IF(H23="","",IF(H23="accepté","oui","non"))
I24: =IF(H24="","",IF(H24="accepté","oui","non"))
I25: =IF(H25="","",IF(H25="accepté","oui","non"))
I26: =IF(H26="","",IF(H26="accepté","oui","non"))
I27: =IF(H27="","",IF(H27="accepté","oui","non"))
I28: =IF(H28="","",IF(H28="accepté","oui","non"))
I29: =IF(H29="","",IF(H29="accepté","oui","non"))
... I47: =IF(H47="","",IF(H47="accepté","oui","non"))

Sheet Prevision
A1: PRÉVISION FIN DE CHANTIER (PFC) ET MARGE PRÉVUE
A3: CFC | B3: Libellé | C3: Budget corrigé | D3: Engagé | E3: Reste à engager | F3: Risques / aléas | G3: PFC (fin de chantier) | H3: Écart au budget corrigé | I3: Suppl. acceptés rattachés | J3: Prix de vente corrigé | K3: Marge prévisionnelle | L3: % Marge prévisionnelle | M3: Marge initiale (réf.) | N3: % Marge initiale (réf.) | O3: Écart de marge (points) | P3: Clé de tri (départage)
A4: ='Budget'!A4 | B4: ='Budget'!B4 | C4: =Budget!$J4 | D4: =SUMIFS(Engagements!$F$32:$F$82,Engagements!$D$32:$D$82,A4) | E4: 199500 | F4: 2500 | G4: =D4+E4+F4 | H4: =G4-C4 | I4: =SUMIFS('Regie-PV-MV'!$F$7:$F$47,'Regie-PV-MV'!$E$7:$E$47,A4,'Regie-PV-MV'!$H$7:$H$47,"accepté") | J4: =Budget!$C4+I4 | K4: =J4-G4 | L4: =IF(J4=0,0,K4/J4) | M4: =Budget!$K4 | N4: =IF(Budget!$C4=0,0,M4/Budget!$C4) | O4: =(L4-N4)*100 | P4: =H4+ROW()/1000000
A5: ='Budget'!A5 | B5: ='Budget'!B5 | C5: =Budget!$J5 | D5: =SUMIFS(Engagements!$F$32:$F$82,Engagements!$D$32:$D$82,A5) | E5: 40000 | F5: 15000 | G5: =D5+E5+F5 | H5: =G5-C5 | I5: =SUMIFS('Regie-PV-MV'!$F$7:$F$47,'Regie-PV-MV'!$E$7:$E$47,A5,'Regie-PV-MV'!$H$7:$H$47,"accepté") | J5: =Budget!$C5+I5 | K5: =J5-G5 | L5: =IF(J5=0,0,K5/J5) | M5: =Budget!$K5 | N5: =IF(Budget!$C5=0,0,M5/Budget!$C5) | O5: =(L5-N5)*100 | P5: =H5+ROW()/1000000
A6: ='Budget'!A6 | B6: ='Budget'!B6 | C6: =Budget!$J6 | D6: =SUMIFS(Engagements!$F$32:$F$82,Engagements!$D$32:$D$82,A6) | E6: 486100 | F6: 2000 | G6: =D6+E6+F6 | H6: =G6-C6 | I6: =SUMIFS('Regie-PV-MV'!$F$7:$F$47,'Regie-PV-MV'!$E$7:$E$47,A6,'Regie-PV-MV'!$H$7:$H$47,"accepté") | J6: =Budget!$C6+I6 | K6: =J6-G6 | L6: =IF(J6=0,0,K6/J6) | M6: =Budget!$K6 | N6: =IF(Budget!$C6=0,0,M6/Budget!$C6) | O6: =(L6-N6)*100 | P6: =H6+ROW()/1000000
A7: ='Budget'!A7 | B7: ='Budget'!B7 | C7: =Budget!$J7 | D7: =SUMIFS(Engagements!$F$32:$F$82,Engagements!$D$32:$D$82,A7) | E7: 10000 | F7: 5000 | G7: =D7+E7+F7 | H7: =G7-C7 | I7: =SUMIFS('Regie-PV-MV'!$F$7:$F$47,'Regie-PV-MV'!$E$7:$E$47,A7,'Regie-PV-MV'!$H$7:$H$47,"accepté") | J7: =Budget!$C7+I7 | K7: =J7-G7 | L7: =IF(J7=0,0,K7/J7) | M7: =Budget!$K7 | N7: =IF(Budget!$C7=0,0,M7/Budget!$C7) | O7: =(L7-N7)*100 | P7: =H7+ROW()/1000000
A8: ='Budget'!A8 | B8: ='Budget'!B8 | C8: =Budget!$J8 | D8: =SUMIFS(Engagements!$F$32:$F$82,Engagements!$D$32:$D$82,A8) | E8: 103100 | F8: 400 | G8: =D8+E8+F8 | H8: =G8-C8 | I8: =SUMIFS('Regie-PV-MV'!$F$7:$F$47,'Regie-PV-MV'!$E$7:$E$47,A8,'Regie-PV-MV'!$H$7:$H$47,"accepté") | J8: =Budget!$C8+I8 | K8: =J8-G8 | L8: =IF(J8=0,0,K8/J8) | M8: =Budget!$K8 | N8: =IF(Budget!$C8=0,0,M8/Budget!$C8) | O8: =(L8-N8)*100 | P8: =H8+ROW()/1000000
A9: ='Budget'!A9 | B9: ='Budget'!B9 | C9: =Budget!$J9 | D9: =SUMIFS(Engagements!$F$32:$F$82,Engagements!$D$32:$D$82,A9) | E9: 50600 | F9: 1800 | G9: =D9+E9+F9 | H9: =G9-C9 | I9: =SUMIFS('Regie-PV-MV'!$F$7:$F$47,'Regie-PV-MV'!$E$7:$E$47,A9,'Regie-PV-MV'!$H$7:$H$47,"accepté") | J9: =Budget!$C9+I9 | K9: =J9-G9 | L9: =IF(J9=0,0,K9/J9) | M9: =Budget!$K9 | N9: =IF(Budget!$C9=0,0,M9/Budget!$C9) | O9: =(L9-N9)*100 | P9: =H9+ROW()/1000000
A10: ='Budget'!A10 | B10: ='Budget'!B10 | C10: =Budget!$J10 | D10: =SUMIFS(Engagements!$F$32:$F$82,Engagements!$D$32:$D$82,A10) | E10: 120200 | F10: 500 | G10: =D10+E10+F10 | H10: =G10-C10 | I10: =SUMIFS('Regie-PV-MV'!$F$7:$F$47,'Regie-PV-MV'!$E$7:$E$47,A10,'Regie-PV-MV'!$H$7:$H$47,"accepté") | J10: =Budget!$C10+I10 | K10: =J10-G10 | L10: =IF(J10=0,0,K10/J10) | M10: =Budget!$K10 | N10: =IF(Budget!$C10=0,0,M10/Budget!$C10) | O10: =(L10-N10)*100 | P10: =H10+ROW()/1000000
A11: ='Budget'!A11 | B11: ='Budget'!B11 | C11: =Budget!$J11 | D11: =SUMIFS(Engagements!$F$32:$F$82,Engagements!$D$32:$D$82,A11) | E11: 10000 | F11: 800 | G11: =D11+E11+F11 | H11: =G11-C11 | I11: =SUMIFS('Regie-PV-MV'!$F$7:$F$47,'Regie-PV-MV'!$E$7:$E$47,A11,'Regie-PV-MV'!$H$7:$H$47,"accepté") | J11: =Budget!$C11+I11 | K11: =J11-G11 | L11: =IF(J11=0,0,K11/J11) | M11: =Budget!$K11 | N11: =IF(Budget!$C11=0,0,M11/Budget!$C11) | O11: =(L11-N11)*100 | P11: =H11+ROW()/1000000
A12: ='Budget'!A12 | B12: ='Budget'!B12 | C12: =Budget!$J12 | D12: =SUMIFS(Engagements!$F$32:$F$82,Engagements!$D$32:$D$82,A12) | E12: 100200 | F12: 400 | G12: =D12+E12+F12 | H12: =G12-C12 | I12: =SUMIFS('Regie-PV-MV'!$F$7:$F$47,'Regie-PV-MV'!$E$7:$E$47,A12,'Regie-PV-MV'!$H$7:$H$47,"accepté") | J12: =Budget!$C12+I12 | K12: =J12-G12 | L12: =IF(J12=0,0,K12/J12) | M12: =Budget!$K12 | N12: =IF(Budget!$C12=0,0,M12/Budget!$C12) | O12: =(L12-N12)*100 | P12: =H12+ROW()/1000000
A13: ='Budget'!A13 | B13: ='Budget'!B13 | C13: =Budget!$J13 | D13: =SUMIFS(Engagements!$F$32:$F$82,Engagements!$D$32:$D$82,A13) | E13: 28200 | F13: 1500 | G13: =D13+E13+F13 | H13: =G13-C13 | I13: =SUMIFS('Regie-PV-MV'!$F$7:$F$47,'Regie-PV-MV'!$E$7:$E$47,A13,'Regie-PV-MV'!$H$7:$H$47,"accepté") | J13: =Budget!$C13+I13 | K13: =J13-G13 | L13: =IF(J13=0,0,K13/J13) | M13: =Budget!$K13 | N13: =IF(Budget!$C13=0,0,M13/Budget!$C13) | O13: =(L13-N13)*100 | P13: =H13+ROW()/1000000
A14: ='Budget'!A14 | B14: ='Budget'!B14 | C14: =Budget!$J14 | D14: =SUMIFS(Engagements!$F$32:$F$82,Engagements!$D$32:$D$82,A14) | E14: 29600 | F14: 2500 | G14: =D14+E14+F14 | H14: =G14-C14 | I14: =SUMIFS('Regie-PV-MV'!$F$7:$F$47,'Regie-PV-MV'!$E$7:$E$47,A14,'Regie-PV-MV'!$H$7:$H$47,"accepté") | J14: =Budget!$C14+I14 | K14: =J14-G14 | L14: =IF(J14=0,0,K14/J14) | M14: =Budget!$K14 | N14: =IF(Budget!$C14=0,0,M14/Budget!$C14) | O14: =(L14-N14)*100 | P14: =H14+ROW()/1000000
A15: ='Budget'!A15 | B15: ='Budget'!B15 | C15: =Budget!$J15 | D15: =SUMIFS(Engagements!$F$32:$F$82,Engagements!$D$32:$D$82,A15) | E15: 30000 | F15: 20000 | G15: =D15+E15+F15 | H15: =G15-C15 | I15: =SUMIFS('Regie-PV-MV'!$F$7:$F$47,'Regie-PV-MV'!$E$7:$E$47,A15,'Regie-PV-MV'!$H$7:$H$47,"accepté") | J15: =Budget!$C15+I15 | K15: =J15-G15 | L15: =IF(J15=0,0,K15/J15) | M15: =Budget!$K15 | N15: =IF(Budget!$C15=0,0,M15/Budget!$C15) | O15: =(L15-N15)*100 | P15: =H15+ROW()/1000000
... A25: ='Budget'!A25 | B25: ='Budget'!B25 | C25: =Budget!$J25 | D25: =SUMIFS(Engagements!$F$32:$F$82,Engagements!$D$32:$D$82,A25) | E25: 85700 | F25: 300 | G25: =D25+E25+F25 | H25: =G25-C25 | I25: =SUMIFS('Regie-PV-MV'!$F$7:$F$47,'Regie-PV-MV'!$E$7:$E$47,A25,'Regie-PV-MV'!$H$7:$H$47,"accepté") | J25: =Budget!$C25+I25 | K25: =J25-G25 | L25: =IF(J25=0,0,K25/J25) | M25: =Budget!$K25 | N25: =IF(Budget!$C25=0,0,M25/Budget!$C25) | O25: =(L25-N25)*100 | P25: =H25+ROW()/1000000
A26: 299 | B26: Divers, travaux imprévus (hors bordereau) | C26: 0 | D26: =SUMIFS(Engagements!$F$32:$F$82,Engagements!$D$32:$D$82,A26) | E26: 0 | F26: 0 | G26: =D26+E26+F26 | H26: =G26-C26 | I26: =SUMIFS('Regie-PV-MV'!$F$7:$F$47,'Regie-PV-MV'!$E$7:$E$47,A26,'Regie-PV-MV'!$H$7:$H$47,"accepté") | J26: =0+I26 | K26: =J26-G26 | L26: =IF(J26=0,0,K26/J26) | M26: 0 | N26: 0 | O26: =(L26-N26)*100 | P26: =H26+ROW()/1000000
A27: TOTAL | B27: Toutes positions CFC, hors bordereau inclus | C27: =SUM(C4:C26) | D27: =SUM(D4:D26) | E27: =SUM(E4:E26) | F27: =SUM(F4:F26) | G27: =SUM(G4:G26) | H27: =SUM(H4:H26) | I27: =SUM(I4:I26) | J27: =SUM(J4:J26) | K27: =SUM(K4:K26) | L27: =IF(J27=0,0,K27/J27) | M27: =SUM(M4:M26) | N27: =IF(SUM('Budget'!$C4:$C25)=0,0,M27/SUM('Budget'!$C4:$C25)) | O27: =(L27-N27)*100

Sheet Cash-flow
A1: CASH-FLOW, FACTURATION ET ENCAISSEMENTS (18 MOIS)
A3: Mois | B3: N° | C3: Facturation planifiée HT | D3: Facturation réelle HT | E3: Cumul planifié | F3: Cumul réel | G3: Encaissements TTC | H3: % Planifié (saisie)
A4: 46023 | B4: 1 | C4: =(Parametres!$B$8*H4)/100 | D4: =SUMIFS(Facturation!$C$4:$C$21,Facturation!$A$4:$A$21,A4) | E4: =SUM($C$4:C4) | F4: =SUM($D$4:D4) | G4: =SUMIFS(Facturation!$G$4:$G$21,Facturation!$H$4:$H$21,"Oui",Facturation!$I$4:$I$21,">="&A4,Facturation!$I$4:$I$21,"<"&EDATE(A4,1)) | H4: 1
A5: 46054 | B5: 2 | C5: =(Parametres!$B$8*H5)/100 | D5: =SUMIFS(Facturation!$C$4:$C$21,Facturation!$A$4:$A$21,A5) | E5: =SUM($C$4:C5) | F5: =SUM($D$4:D5) | G5: =SUMIFS(Facturation!$G$4:$G$21,Facturation!$H$4:$H$21,"Oui",Facturation!$I$4:$I$21,">="&A5,Facturation!$I$4:$I$21,"<"&EDATE(A5,1)) | H5: 2
A6: 46082 | B6: 3 | C6: =(Parametres!$B$8*H6)/100 | D6: =SUMIFS(Facturation!$C$4:$C$21,Facturation!$A$4:$A$21,A6) | E6: =SUM($C$4:C6) | F6: =SUM($D$4:D6) | G6: =SUMIFS(Facturation!$G$4:$G$21,Facturation!$H$4:$H$21,"Oui",Facturation!$I$4:$I$21,">="&A6,Facturation!$I$4:$I$21,"<"&EDATE(A6,1)) | H6: 4
A7: 46113 | B7: 4 | C7: =(Parametres!$B$8*H7)/100 | D7: =SUMIFS(Facturation!$C$4:$C$21,Facturation!$A$4:$A$21,A7) | E7: =SUM($C$4:C7) | F7: =SUM($D$4:D7) | G7: =SUMIFS(Facturation!$G$4:$G$21,Facturation!$H$4:$H$21,"Oui",Facturation!$I$4:$I$21,">="&A7,Facturation!$I$4:$I$21,"<"&EDATE(A7,1)) | H7: 6
A8: 46143 | B8: 5 | C8: =(Parametres!$B$8*H8)/100 | D8: =SUMIFS(Facturation!$C$4:$C$21,Facturation!$A$4:$A$21,A8) | E8: =SUM($C$4:C8) | F8: =SUM($D$4:D8) | G8: =SUMIFS(Facturation!$G$4:$G$21,Facturation!$H$4:$H$21,"Oui",Facturation!$I$4:$I$21,">="&A8,Facturation!$I$4:$I$21,"<"&EDATE(A8,1)) | H8: 8
A9: 46174 | B9: 6 | C9: =(Parametres!$B$8*H9)/100 | D9: =SUMIFS(Facturation!$C$4:$C$21,Facturation!$A$4:$A$21,A9) | E9: =SUM($C$4:C9) | F9: =SUM($D$4:D9) | G9: =SUMIFS(Facturation!$G$4:$G$21,Facturation!$H$4:$H$21,"Oui",Facturation!$I$4:$I$21,">="&A9,Facturation!$I$4:$I$21,"<"&EDATE(A9,1)) | H9: 9
A10: 46204 | B10: 7 | C10: =(Parametres!$B$8*H10)/100 | D10: =SUMIFS(Facturation!$C$4:$C$21,Facturation!$A$4:$A$21,A10) | E10: =SUM($C$4:C10) | F10: =SUM($D$4:D10) | G10: =SUMIFS(Facturation!$G$4:$G$21,Facturation!$H$4:$H$21,"Oui",Facturation!$I$4:$I$21,">="&A10,Facturation!$I$4:$I$21,"<"&EDATE(A10,1)) | H10: 9
A11: 46235 | B11: 8 | C11: =(Parametres!$B$8*H11)/100 | D11: =SUMIFS(Facturation!$C$4:$C$21,Facturation!$A$4:$A$21,A11) | E11: =SUM($C$4:C11) | F11: =SUM($D$4:D11) | G11: =SUMIFS(Facturation!$G$4:$G$21,Facturation!$H$4:$H$21,"Oui",Facturation!$I$4:$I$21,">="&A11,Facturation!$I$4:$I$21,"<"&EDATE(A11,1)) | H11: 8
A12: 46266 | B12: 9 | C12: =(Parametres!$B$8*H12)/100 | D12: =SUMIFS(Facturation!$C$4:$C$21,Facturation!$A$4:$A$21,A12) | E12: =SUM($C$4:C12) | F12: =SUM($D$4:D12) | G12: =SUMIFS(Facturation!$G$4:$G$21,Facturation!$H$4:$H$21,"Oui",Facturation!$I$4:$I$21,">="&A12,Facturation!$I$4:$I$21,"<"&EDATE(A12,1)) | H12: 8
A13: 46296 | B13: 10 | C13: =(Parametres!$B$8*H13)/100 | D13: =SUMIFS(Facturation!$C$4:$C$21,Facturation!$A$4:$A$21,A13) | E13: =SUM($C$4:C13) | F13: =SUM($D$4:D13) | G13: =SUMIFS(Facturation!$G$4:$G$21,Facturation!$H$4:$H$21,"Oui",Facturation!$I$4:$I$21,">="&A13,Facturation!$I$4:$I$21,"<"&EDATE(A13,1)) | H13: 7
A14: 46327 | B14: 11 | C14: =(Parametres!$B$8*H14)/100 | D14: =SUMIFS(Facturation!$C$4:$C$21,Facturation!$A$4:$A$21,A14) | E14: =SUM($C$4:C14) | F14: =SUM($D$4:D14) | G14: =SUMIFS(Facturation!$G$4:$G$21,Facturation!$H$4:$H$21,"Oui",Facturation!$I$4:$I$21,">="&A14,Facturation!$I$4:$I$21,"<"&EDATE(A14,1)) | H14: 6
A15: 46357 | B15: 12 | C15: =(Parametres!$B$8*H15)/100 | D15: =SUMIFS(Facturation!$C$4:$C$21,Facturation!$A$4:$A$21,A15) | E15: =SUM($C$4:C15) | F15: =SUM($D$4:D15) | G15: =SUMIFS(Facturation!$G$4:$G$21,Facturation!$H$4:$H$21,"Oui",Facturation!$I$4:$I$21,">="&A15,Facturation!$I$4:$I$21,"<"&EDATE(A15,1)) | H15: 6
... A21: 46539 | B21: 18 | C21: =(Parametres!$B$8*H21)/100 | D21: =SUMIFS(Facturation!$C$4:$C$21,Facturation!$A$4:$A$21,A21) | E21: =SUM($C$4:C21) | F21: =SUM($D$4:D21) | G21: =SUMIFS(Facturation!$G$4:$G$21,Facturation!$H$4:$H$21,"Oui",Facturation!$I$4:$I$21,">="&A21,Facturation!$I$4:$I$21,"<"&EDATE(A21,1)) | H21: 3

Sheet Dashboard
A1: DASHBOARD, SYNTHÈSE DU CHANTIER
A3: PRIX DE VENTE CORRIGÉ (CHF)
A4: ='Prevision'!J27
A5: PFC TOTALE, PRÉVISION FIN DE CHANTIER (CHF)
A6: ='Prevision'!G27
A7: MARGE PRÉVISIONNELLE (CHF)
A8: ='Prevision'!K27
A9: MARGE PRÉVISIONNELLE (%)
A10: ='Prevision'!L27
A11: DÉRIVE DE MARGE VS MARGE INITIALE (POINTS)
A12: ='Prevision'!O27
A13: % ENGAGÉ (ENGAGÉ TOTAL / BUDGET CORRIGÉ)
A14: ='Engagements'!D28/'Budget'!J$26
A15: % FACTURÉ (FACTURÉ CUMULÉ / VENTE CORRIGÉE)
A16: ='Facturation'!J12/'Prevision'!J27
A17: AVANCEMENT TEMPS (MOIS ÉCOULÉS / DURÉE TOTALE)
A18: =(DATEDIF(Parametres!$B$19,Parametres!$B$7,"m")+1)/Parametres!$B$10
A19: MARGE VISÉE (PARAMÈTRES, %)
A20: =Parametres!$B$9
D22: Statut global marge | E22: =IF(A8<0,"ROUGE",IF(A12<-1,"ORANGE","VERT"))
A24: Légende, règles des feux tricolores
A25: ROUGE | B25: Marge prévisionnelle totale négative : le chantier finirait à perte.
A26: ORANGE | B26: Dérive de marge inférieure à -1 point par rapport à la marge initiale (dégradation signée, pas une simple valeur absolue).
A27: VERT | B27: Aucune des deux conditions ci-dessus : situation sous contrôle.
A28: Top 5 des écarts PFC vs budget (par position CFC, des économies peuvent apparaître)
A29: Rang | B29: CFC | C29: Libellé | D29: Écart (CHF)
A30: 1 | B30: =INDEX('Prevision'!$A$4:$A$26,MATCH(H30,'Prevision'!$P$4:$P$26,0)) | C30: =INDEX('Prevision'!$B$4:$B$26,MATCH(H30,'Prevision'!$P$4:$P$26,0)) | D30: =INDEX('Prevision'!$H$4:$H$26,MATCH(H30,'Prevision'!$P$4:$P$26,0)) | H30: =LARGE('Prevision'!$P$4:$P$26,1)
A31: 2 | B31: =INDEX('Prevision'!$A$4:$A$26,MATCH(H31,'Prevision'!$P$4:$P$26,0)) | C31: =INDEX('Prevision'!$B$4:$B$26,MATCH(H31,'Prevision'!$P$4:$P$26,0)) | D31: =INDEX('Prevision'!$H$4:$H$26,MATCH(H31,'Prevision'!$P$4:$P$26,0)) | H31: =LARGE('Prevision'!$P$4:$P$26,2)
A32: 3 | B32: =INDEX('Prevision'!$A$4:$A$26,MATCH(H32,'Prevision'!$P$4:$P$26,0)) | C32: =INDEX('Prevision'!$B$4:$B$26,MATCH(H32,'Prevision'!$P$4:$P$26,0)) | D32: =INDEX('Prevision'!$H$4:$H$26,MATCH(H32,'Prevision'!$P$4:$P$26,0)) | H32: =LARGE('Prevision'!$P$4:$P$26,3)
A33: 4 | B33: =INDEX('Prevision'!$A$4:$A$26,MATCH(H33,'Prevision'!$P$4:$P$26,0)) | C33: =INDEX('Prevision'!$B$4:$B$26,MATCH(H33,'Prevision'!$P$4:$P$26,0)) | D33: =INDEX('Prevision'!$H$4:$H$26,MATCH(H33,'Prevision'!$P$4:$P$26,0)) | H33: =LARGE('Prevision'!$P$4:$P$26,4)
A34: 5 | B34: =INDEX('Prevision'!$A$4:$A$26,MATCH(H34,'Prevision'!$P$4:$P$26,0)) | C34: =INDEX('Prevision'!$B$4:$B$26,MATCH(H34,'Prevision'!$P$4:$P$26,0)) | D34: =INDEX('Prevision'!$H$4:$H$26,MATCH(H34,'Prevision'!$P$4:$P$26,0)) | H34: =LARGE('Prevision'!$P$4:$P$26,5)

Sheet Analyse
A1: ANALYSE, CONTRÔLES AUTOMATIQUES
A3: N° | B3: Contrôle | C3: Valeur constatée | D3: Référence / seuil | E3: Résultat | F3: Message
A4: 1 | B4: Positions avec engagé supérieur au budget corrigé | C4: =SUMPRODUCT((Engagements!$D$5:$D$26>Engagements!$C$5:$C$26)*1) | D4: =0 | E4: =IF(C4>D4,"ALERTE","OK") | F4: {="Positions en dépassement : "&_xlfn.TEXTJOIN(", ",TRUE,IF(Engagements!$D$5:$D$26>Engagements!$C$5:$C$26,Engagements!$A$5:$A$26,""))&" (détail dans la feuille Engagements)."}
A5: 2 | B5: Facturé cumulé supérieur à l'engagé total (global) | C5: =Facturation!$J$22 | D5: =Engagements!$D$28 | E5: =IF(C5>D5,"ALERTE","OK") | F5: ="Facturé cumulé "&TEXT(C5,"#'##0")&" CHF vs engagé total "&TEXT(D5,"#'##0")&" CHF."
A6: 3 | B6: Position sans budget (hors bordereau) mais avec engagements | C6: =SUMPRODUCT((COUNTIF(Budget!$A$4:$A$25,Engagements!$D$32:$D$82)=0)*(Engagements!$F$32:$F$82>0)) | D6: =0 | E6: =IF(C6>D6,"ALERTE","OK") | F6: {="Lignes du journal Engagements avec un CFC absent du bordereau Budget : "&_xlfn.TEXTJOIN(", ",TRUE,IF(COUNTIF(Budget!$A$4:$A$25,Engagements!$D$32:$D$82)=0,Engagements!$D$32:$D$82,""))&"."}
A7: 4 | B7: Suppléments en attente (statut annoncé) supérieurs à 2% de la vente | C7: =SUMIFS('Regie-PV-MV'!$F$7:$F$47,'Regie-PV-MV'!$H$7:$H$47,"annoncé") | D7: =0.02*Budget!$C$26 | E7: =IF(C7>D7,"ALERTE","OK") | F7: ="Total annoncé vs seuil de 2% de la vente totale (voir feuille Régie-PV-MV)."
A8: 5 | B8: Retenue de garantie réellement appliquée vs plafond contractuel | C8: =Facturation!$D$22 | D8: =Parametres!$B$8*Parametres!$B$14 | E8: =IF(C8>D8,"ALERTE","OK") | F8: ="Retenue réellement appliquée (feuille Facturation, plafonnée) vs plafond contractuel de 2% du prix de vente."
A9: 6 | B9: Marge prévisionnelle globale inférieure à 50% de la marge initiale | C9: =Prevision!$K$27 | D9: =0.5*Prevision!$M$27 | E9: =IF(C9<D9,"ALERTE","OK") | F9: ="Marge prévisionnelle totale vs 50% de la marge initiale totale."
